aiohttp_apischema/__init__.py
aiohttp_apischema/generator.py
aiohttp_apischema/py.typed
aiohttp_apischema/response.py
aiohttp_apischema/swagger-ui/favicon-16x16.png
aiohttp_apischema/swagger-ui/favicon-32x32.png
aiohttp_apischema/swagger-ui/index.css
aiohttp_apischema/swagger-ui/index.html
aiohttp_apischema/swagger-ui/oauth2-redirect.html
aiohttp_apischema/swagger-ui/swagger-initializer.js
aiohttp_apischema/swagger-ui/swagger-ui-bundle.js
aiohttp_apischema/swagger-ui/swagger-ui-es-bundle-core.js
aiohttp_apischema/swagger-ui/swagger-ui-es-bundle.js
aiohttp_apischema/swagger-ui/swagger-ui-standalone-preset.js
aiohttp_apischema/swagger-ui/swagger-ui.css
aiohttp_apischema/swagger-ui/swagger-ui.js
aiohttp_apischema-0.0.2.dist-info/licenses/LICENSE
aiohttp_apischema-0.0.2.dist-info/METADATA
aiohttp_apischema-0.0.2.dist-info/WHEEL
aiohttp_apischema-0.0.2.dist-info/top_level.txt
aiohttp_apischema-0.0.2.dist-info/RECORD
