Metadata-Version: 2.4
Name: aiohttp-apischema
Version: 0.0.2
Summary: Generate a schema and validate user input from types
License: Apache License
Project-URL: Homepage, https://github.com/aio-libs/aiohttp-apischema
Project-URL: Issues, https://github.com/aio-libs/aiohttp-apischema/issues
Classifier: Programming Language :: Python
Classifier: Programming Language :: Python :: 3
Classifier: License :: OSI Approved :: Apache Software License
Classifier: Operating System :: OS Independent
Classifier: Intended Audience :: Developers
Classifier: Topic :: Internet :: WWW/HTTP
Classifier: Framework :: AsyncIO
Classifier: Framework :: aiohttp
Classifier: Development Status :: 2 - Pre-Alpha
Requires-Python: >=3.10
License-File: LICENSE
Requires-Dist: aiohttp>=3.9
Requires-Dist: pydantic>=2
Requires-Dist: typing-extensions; python_version < "3.13"
Dynamic: license-file
